fastapi_static_files/__init__.py
fastapi_static_files/staticfiles.py
fastapi_static_files/templates/index.html
fastapi_static_files-0.1.0.dist-info/METADATA
fastapi_static_files-0.1.0.dist-info/WHEEL
fastapi_static_files-0.1.0.dist-info/licenses/LICENSE
fastapi_static_files-0.1.0.dist-info/RECORD
